noteslib.py
noteslib-2.1.1.dist-info/WHEEL
noteslib-2.1.1.dist-info/METADATA
noteslib-2.1.1.dist-info/RECORD
