Metadata-Version: 2.1
Name: noteslib
Version: 2.1.1
Summary: Python classes for manipulating Lotus Notes/Domino objects via COM
Author: Robert Follek
Author-email: bfollek@gmail.com
Maintainer: Marcelo Huerta
Maintainer-email: richieadler@gmail.com
Requires-Python: >=3.7
Classifier: Development Status :: 5 - Production/Stable
Classifier: Environment :: Win32 (MS Windows)
Classifier: Intended Audience :: Developers
Classifier: License :: OSI Approved :: MIT License
Classifier: Operating System :: Microsoft :: Windows
Classifier: Programming Language :: Python :: 3 :: Only
Classifier: Topic :: Database
Classifier: Topic :: Software Development :: Libraries :: Python Modules
Requires-Dist: pywin32
